README.txt
setup.cfg
setup.py
cvlops/__init__.py
cvlops.egg-info/PKG-INFO
cvlops.egg-info/SOURCES.txt
cvlops.egg-info/dependency_links.txt
cvlops.egg-info/requires.txt
cvlops.egg-info/top_level.txt
cvlops/utils/__init__.py
cvlops/utils/mail.py
jinja2/generic.jinja2