Metadata-Version: 1.0
Name: cvlops
Version: 1.11
Summary: CVISIONLAB OPS Python Utils
Home-page: https://github.com/cvisionlabops/cvlops-python
Author: Skubriev Vladimir
Author-email: skubriev@cvisionlab.com
License: GPL
Platform: UNKNOWN
